VinToVinproxy/__init__.py
VinToVinproxy/main.py
vp_converter-0.0.1.dist-info/METADATA
vp_converter-0.0.1.dist-info/WHEEL
vp_converter-0.0.1.dist-info/top_level.txt
vp_converter-0.0.1.dist-info/RECORD
