Metadata-Version: 2.1
Name: vp-converter
Version: 0.0.1
Summary: Vin to vin proxy conversion
Home-page: UNKNOWN
Author: Aman Kumar Gupta
Author-email: amankumar.gupta@maruti.co.in
License: UNKNOWN
Keywords: python,vin
Platform: UNKNOWN
Classifier: Development Status :: 1 - Planning
Classifier: Intended Audience :: Developers
Classifier: Programming Language :: Python :: 3
Classifier: Operating System :: Unix
Classifier: Operating System :: MacOS :: MacOS X
Classifier: Operating System :: Microsoft :: Windows
